simple_sds011/__init__.py
simple_sds011-0.0.7.dist-info/LICENSE.txt
simple_sds011-0.0.7.dist-info/METADATA
simple_sds011-0.0.7.dist-info/WHEEL
simple_sds011-0.0.7.dist-info/top_level.txt
simple_sds011-0.0.7.dist-info/RECORD
