Metadata-Version: 2.1
Name: simple-sds011
Version: 0.0.7
Summary: A minimal library for SDS011 particulate sensors.
Home-page: https://github.com/krumphauchicken/simple-sds011
Author: Brian Frick
License: LICENSE.txt
Platform: UNKNOWN
Classifier: Development Status :: 3 - Alpha
Classifier: Environment :: Console
Classifier: License :: OSI Approved :: MIT License
Classifier: Natural Language :: English
Classifier: Operating System :: POSIX :: Linux
Classifier: Programming Language :: Python :: 3 :: Only
Classifier: Topic :: Scientific/Engineering :: Atmospheric Science
Requires-Dist: pyserial (>=3.0)
